fsorg/entry.py
fsorg/fsorgfile.py
fsorg/main.py
fsorg-1.0.4.dist-info/entry_points.txt
fsorg-1.0.4.dist-info/LICENSE.md
fsorg-1.0.4.dist-info/WHEEL
fsorg-1.0.4.dist-info/METADATA
fsorg-1.0.4.dist-info/RECORD
