Metadata-Version: 2.1
Name: fsorg
Version: 1.0.4
Summary: Create a directory structure by describing it
License: MIT
Author: ewen-lbh
Author-email: ewen.lebihan7@gmail.com
Requires-Python: >=3.7,<4.0
Classifier: License :: OSI Approved :: MIT License
Classifier: Programming Language :: Python :: 3
Classifier: Programming Language :: Python :: 3.7
Classifier: Programming Language :: Python :: 3.8
Requires-Dist: pyfiglet (>=0.8.post1,<0.9)
Requires-Dist: rm (>=2019.4.13,<2020.0.0)
